sum_matcher/__init__.py
sum_matcher/sum_matcher.cp310-win_amd64.pyd
sum_matcher-0.3.0.dist-info/LICENSE
sum_matcher-0.3.0.dist-info/METADATA
sum_matcher-0.3.0.dist-info/WHEEL
sum_matcher-0.3.0.dist-info/top_level.txt
sum_matcher-0.3.0.dist-info/RECORD
